ancient_science_of_numbers/__init__.py
ancient_science_of_numbers/analysis.py
ancient_science_of_numbers/colors.py
ancient_science_of_numbers/core.py
ancient_science_of_numbers/cycles.py
ancient_science_of_numbers/data.py
ancient_science_of_numbers/harmonies.py
ancient_science_of_numbers/keynotes.py
ancient_science_of_numbers/letters.py
ancient_science_of_numbers-0.1.0.dist-info/licenses/LICENSE
ancient_science_of_numbers-0.1.0.dist-info/METADATA
ancient_science_of_numbers-0.1.0.dist-info/WHEEL
ancient_science_of_numbers-0.1.0.dist-info/top_level.txt
ancient_science_of_numbers-0.1.0.dist-info/RECORD
