Metadata-Version: 2.4
Name: ancient-science-of-numbers
Version: 0.1.0
Summary: A Python library implementing the numerology system from 'The Ancient Science of Numbers' by Luo Clement (1908)
Home-page: https://github.com/sigasaint/ancient-science-of-numbers
Author: Mthabis W. Mkwananzi
Author-email: 
License: MIT
Project-URL: Source, https://github.com/sigasaint/ancient-science-of-numbers
Project-URL: Bug Tracker, https://github.com/sigasaint/ancient-science-of-numbers/issues
Project-URL: Documentation, https://github.com/sigasaint/ancient-science-of-numbers#readme
Keywords: numerology,numbers,ancient science, Luo Clement
Classifier: Development Status :: 3 - Alpha
Classifier: Intended Audience :: Developers
Classifier: Topic :: Software Development :: Libraries :: Python Modules
Classifier: License :: OSI Approved :: MIT License
Classifier: Programming Language :: Python :: 3
Classifier: Programming Language :: Python :: 3 :: Only
Classifier: Programming Language :: Python :: 3.9
Classifier: Programming Language :: Python :: 3.10
Classifier: Programming Language :: Python :: 3.11
Classifier: Programming Language :: Python :: 3.12
Classifier: Operating System :: OS Independent
Requires-Python: >=3.9,<4
License-File: LICENSE
Provides-Extra: dev
Requires-Dist: pytest>=7.0.0; extra == "dev"
Requires-Dist: pytest-cov>=4.0.0; extra == "dev"
Requires-Dist: wheel>=0.40.0; extra == "dev"
Requires-Dist: build>=0.10.0; extra == "dev"
Dynamic: author
Dynamic: classifier
Dynamic: description
Dynamic: description-content-type
Dynamic: home-page
Dynamic: keywords
Dynamic: license
Dynamic: license-file
Dynamic: project-url
Dynamic: provides-extra
Dynamic: requires-python
Dynamic: summary
